Metadata-Version: 1.0
Name: jiggle
Version: 0.1
Summary: simple mouse jiggler
Home-page: https://github.com/OpenJarbas/jiggle
Author: jarbasAI
Author-email: jarbasai@mailfence.com
License: Apache2.0
Platform: UNKNOWN
